moban_velocity/__init__.py
moban_velocity/_version.py
moban_velocity/engine.py
moban_velocity-0.0.2.dist-info/LICENSE
moban_velocity-0.0.2.dist-info/METADATA
moban_velocity-0.0.2.dist-info/WHEEL
moban_velocity-0.0.2.dist-info/top_level.txt
moban_velocity-0.0.2.dist-info/RECORD
