Metadata-Version: 2.1
Name: moban-velocity
Version: 0.0.2
Summary: Provide velocity templating capability to moban
Home-page: https://github.com/moremoban/moban-velocity
Author: Ayan Banerjee, C.W. et al
Author-email: wangc_2011@hotmail.com
License: MIT
Download-URL: https://github.com/moremoban/moban-velocity/archive/0.0.2.tar.gz
Keywords: python
Platform: UNKNOWN
Classifier: Topic :: Software Development :: Libraries
Classifier: Programming Language :: Python
Classifier: Intended Audience :: Developers
Classifier: Programming Language :: Python :: 2.6
Classifier: Programming Language :: Python :: 2.7
Classifier: Programming Language :: Python :: 3.3
Classifier: Programming Language :: Python :: 3.4
Classifier: Programming Language :: Python :: 3.5
Classifier: Programming Language :: Python :: 3.6
Classifier: Programming Language :: Python :: 3.7
Classifier: Programming Language :: Python :: 3.8
Requires-Dist: lml (>=0.0.7)
Requires-Dist: airspeed
